[{"id":17,"name":"Ada","images":["https://static.wikia.nocookie.net/naruto/images/f/f6/Ada_Infobox_Image.png"],"debut":{"manga":"Boruto Chapter #56","appearsIn":"Manga"},"family":{"brother":"Daemon"},"personal":{"sex":"Female","age":{"Boruto Manga":"16"},"kekkeiGenkai":"Senrigan","affiliation":["Kara","Konohagakure"],"titles":["エイダEida"]},"tools":[]},{"id":80,"name":"Ao","images":["https://static.wikia.nocookie.net/naruto/images/7/72/Ao.png","https://static.wikia.nocookie.net/naruto/images/4/4c/Ao_Part_III.png"],"debut":{"manga":"Naruto Chapter #454","anime":"Naruto Shippūden Episode #199","novel":"Sasuke Shinden: Book of Sunrise  (Mentioned)","game":"Naruto Shippūden: Ultimate Ninja Impact","appearsIn":"Anime, Manga, Novel, Game"},"jutsu":["Barrier Talisman: Armoured Eye","Sensing Technique","Sensing Water Sphere","Water Release: Water Colliding Wave"],"natureType":["Water Release","Yin Release"],"personal":{"birthdate":"August 1","sex":"Male","age":{"Part II":"46"},"status":"Deceased","height":{"Part II":"182cm"},"weight":{"Part II":"70.9kg"},"bloodType":"A","kekkeiGenkai":"Byakugan","classification":["Sensor Type","Hunter-nin"],"occupation":["Fifth Mizukage's Bodyguard","Captain of the Sensor Division of the Allied Shinobi Forces","Outer"],"affiliation":["Kirigakure","Allied Shinobi Forces","Kara"],"team":"Sensor Division","partner":"Heki","titles":["青Ao","byakuganKiller(白眼殺し,Byakugangoroshi)grass(草,Kusa)"]},"rank":{"ninjaRank":{"Part II":"Jōnin"}},"tools":["Chakra Blade","Jutsu Absorption Arm","Mirror Drone","Shinobi Gauntlet"],"voiceActors":{"japanese":"Tadahisa Saizen","english":"Steven Blum"}},{"id":125,"name":"Boro","images":["https://static.wikia.nocookie.net/naruto/images/6/63/Boro.png"],"debut":{"manga":"Boruto Chapter #15","anime":"Boruto Episode #157","game":"Naruto x Boruto: Ninja Voltage","appearsIn":"Anime, Manga, Game"},"jutsu":["Genjutsu Communication","Lava Release: Planet-Branding Blast","Self-Healing Technique","Water Release: Water Formation Wall"],"natureType":["Lava Release","Fire Release","Earth Release","Water Release","Yin Release"],"personal":{"sex":"Male","status":"Deceased","kekkeiGenkai":"Lava Release","occupation":["Inner","Cult Leader"],"affiliation":"Kara"},"tools":["Dark Cloud","Space-Time Gate"],"voiceActors":{"japanese":"Kenta Miyake","english":"Dave B. Mitchell"}},{"id":128,"name":"Bug","images":["https://static.wikia.nocookie.net/naruto/images/7/7d/Bug.png"],"debut":{"manga":"Boruto Chapter #56","appearsIn":"Manga"},"personal":{"sex":"Male","occupation":["Outer","Cultist"],"affiliation":"Kara"}},{"id":141,"name":"Chibi","images":["https://static.wikia.nocookie.net/naruto/images/d/d2/Chibi.png"],"debut":{"manga":"Naruto Chapter #445","anime":"Naruto Shippūden Episode #172","appearsIn":"Anime, Manga"},"personal":{"sex":"Male","species":"Dog","age":{"Part II":"2"},"status":"Deceased","affiliation":"Ame Orphans\"Ame Orphans\" is not in the list (Allied Shinobi Forces, Akatsuki, Root, Kara, Pale Blue Valley, Daidai Village, Aburame Clan, Academy, Advanced Technology Research Institute, Akagahara, ...) of allowed values for the \"Affiliation\" property."}},{"id":159,"name":"Code","images":["https://static.wikia.nocookie.net/naruto/images/3/38/Code.png"],"debut":{"manga":"Boruto Chapter #15","anime":"Boruto Episode #157","game":"Naruto x Boruto: Ninja Voltage","appearsIn":"Anime, Manga, Game"},"jutsu":["Claw Grime (Manga only)","Claw Mark","Genjutsu Communication","Kāma"],"natureType":["Yin Release"],"personal":{"sex":"Male","occupation":["Inner","Leader of Kara"],"affiliation":"Kara","titles":["コードKōdo"]},"tools":["Microscopic Scientific Ninja Tools (Manga only)","Space-Time Gate"],"voiceActors":{"japanese":"Junta Terashima","english":"Jacob Hopkins"}},{"id":165,"name":"Daemon","images":["https://static.wikia.nocookie.net/naruto/images/2/25/Daemon_infobox.png"],"debut":{"manga":"Boruto Chapter #59","appearsIn":"Manga"},"family":{"sister":"Ada"},"jutsu":["Reflection Shinjutsu"],"personal":{"sex":"Male","affiliation":["Kara","Konohagakure"]},"tools":[]},{"id":192,"name":"Deepa","images":["https://static.wikia.nocookie.net/naruto/images/6/69/Deepa.png"],"debut":{"anime":"Boruto Episode #157","appearsIn":"Anime"},"jutsu":["Carbon Armour","Carbon Control","Carbon Ring","Carbon Whip","Genjutsu Communication"],"natureType":["Yin Release"],"personal":{"sex":"Male","status":"Deceased","occupation":"Inner","affiliation":"Kara","partner":"Victor"},"voiceActors":{"japanese":"Tetsuya Kakihara","english":"Chris Hackney"}},{"id":194,"name":"Delta","images":["https://static.wikia.nocookie.net/naruto/images/7/7c/Delta_Infobox.png"],"debut":{"manga":"Boruto Chapter #15","anime":"Boruto Episode #157","game":"Naruto x Boruto: Ninja Voltage","appearsIn":"Anime, Manga, Game"},"family":{"genetic source":"Akebi Sanzu","creator/father":"Amado Sanzu"},"jutsu":["Genjutsu Communication"],"natureType":["Yin Release"],"personal":{"sex":"Female","occupation":"Inner  (Former)","affiliation":["Kara","Konohagakure  (Manga only)"],"titles":["デルタDeruta"]},"tools":["Absorbing Eye","Microscopic Scientific Ninja Tools","Space-Time Gate","Spy Drone"],"voiceActors":{"japanese":"Houko Kuwashima","english":"Amber Lee Connors"}},{"id":274,"name":"Kiseru Gankubi","images":["https://static.wikia.nocookie.net/naruto/images/1/1f/Kiseru_Gankubi.png"],"debut":{"anime":"Boruto Episode #276","appearsIn":"Anime"},"jutsu":["Fire Release Chakra Mode","Fire Release: Deep Flame Explosion","Fire Release: Flame Attack","Fire Release: Flame Bullet","Fire Release: Flaming Hail","Fire Release: Phoenix Sage Fire Technique","Mystical Palm Technique"],"natureType":["Fire Release"],"personal":{"sex":"Male","classification":"Medical-nin","occupation":"Outer  (Former)","affiliation":["Konohagakure","Kara"],"team":"Five Great Countries' Joint Investigation Team"},"rank":{"ninjaRank":{"Boruto Manga":"Anbu"}},"voiceActors":{"japanese":"Katsunori Okai"}},{"id":283,"name":"Garō","images":["https://static.wikia.nocookie.net/naruto/images/0/07/Gar%C5%8D.png"],"debut":{"manga":"Boruto Chapter #24","anime":"Boruto Episode #188","appearsIn":"Anime, Manga"},"personal":{"sex":"Male","status":"Deceased","occupation":"Outer","affiliation":"Kara"},"tools":["Shinobi Gauntlet"],"voiceActors":{"japanese":"Hiroaki Tajiri","english":"John Eric Bentley"}},{"id":396,"name":"Himeyuri","images":["https://static.wikia.nocookie.net/naruto/images/2/24/Himeyuri.png"],"debut":{"anime":"Naruto Shippūden Episode #485","appearsIn":"Anime"},"personal":{"sex":"Female","status":"Deceased","occupation":"Businesswoman","affiliation":"Himeyuri Company\"Himeyuri Company\" is not in the list (Allied Shinobi Forces, Akatsuki, Root, Kara, Pale Blue Valley, Daidai Village, Aburame Clan, Academy, Advanced Technology Research Institute, Akagahara, ...) of allowed values for the \"Affiliation\" property."},"voiceActors":{"japanese":"Mariko Higashiuchi","english":"Colleen O'Shaughnessey"}},{"id":400,"name":"Hinoki","images":["https://static.wikia.nocookie.net/naruto/images/b/be/Hinoki.png"],"debut":{"game":"Naruto: Path of the Ninja 2","appearsIn":"Game"},"family":{"granddaughter":"Nazuna"},"personal":{"sex":"Male","occupation":"Village Head","affiliation":"Valley of Great Evil\"Valley of Great Evil\" is not in the list (Allied Shinobi Forces, Akatsuki, Root, Kara, Pale Blue Valley, Daidai Village, Aburame Clan, Academy, Advanced Technology Research Institute, Akagahara, ...) of allowed values for the \"Affiliation\" property."}},{"id":487,"name":"Iwa Doctor","images":["https://static.wikia.nocookie.net/naruto/images/f/ff/Iwa_Doctor_Infobox.png"],"debut":{"anime":"Boruto Episode #78","appearsIn":"Anime"},"family":{"creation":"Sekiei"},"personal":{"sex":"Male","status":"Presumed Deceased","occupation":["Doctor","Outer"],"affiliation":["Iwagakure","Kara"]},"voiceActors":{"japanese":"Tomohisa Asō","english":"Kyle Hebert"}},{"id":510,"name":"Jigen","images":["https://static.wikia.nocookie.net/naruto/images/5/54/Jigen_Infobox.png"],"debut":{"manga":"Boruto Chapter #15","anime":"Boruto Episode #157","game":"Naruto x Boruto: Ninja Voltage","appearsIn":"Anime, Manga, Game"},"family":{"host":"Isshiki Ōtsutsuki"},"jutsu":["Kāma"],"personal":{"sex":"Male","species":"Celestial Being","status":"Deceased","occupation":["Monk","Vessel","Inner"],"affiliation":"Kara"},"voiceActors":{"japanese":"Kenjirō Tsuda","english":"Keith Silverstein"}},{"id":600,"name":"Koji Kashin","images":["https://static.wikia.nocookie.net/naruto/images/f/f2/Koji.png"],"debut":{"manga":"Boruto Chapter #15","anime":"Boruto Episode #53","game":"Naruto x Boruto: Ninja Voltage","appearsIn":"Anime, Manga, Game"},"family":{"creator":"Amado Sanzu","genetic template":"Jiraiya"},"jutsu":["Big Ball Rasengan","Earth Release: Swamp of the Underworld","Fire Release: Big Flame Bullet","Fire Release: Flame Attack","Fire Release: Flame Bullet","Genjutsu Communication","Needle Jizō","Rasengan","Reverse Summoning Technique","Sage Art: Five Fire Gods' Fan of Flames","Sage Mode","Sealing Technique: Frog Suppression","Shadow Clone Technique","Summoning Technique (Toad)","Summoning: Food Cart Destroyer Technique","Toad Oil Bullet","Toad Smoke Technique (Anime only)","Toad Spying Technique","True Fire of Samadhi","Ultra-Big Ball Rasengan","Wild Lion's Mane Technique"],"natureType":["Fire Release","Earth Release","Yin Release"],"personal":{"sex":"Male","classification":"Sage","occupation":"Inner  (Former)","affiliation":["Kara","Mount Myōboku"]},"voiceActors":{"japanese":"Yūichi Nakamura","english":"Kaiji Tang"}},{"id":609,"name":"Kawaki","images":["https://static.wikia.nocookie.net/naruto/images/e/ef/Kawaki_infobox.png"],"debut":{"manga":"Boruto Chapter #1","anime":"Boruto Episode #1","game":"Naruto x Boruto: Ninja Voltage","appearsIn":"Anime, Manga, Game"},"family":{"father":"Kokatsu","adoptive father":"Naruto Uzumaki","adoptive mother":"Hinata Uzumaki","adoptive brother":"Boruto Uzumaki","adoptive sister":"Himawari Uzumaki","adoptive grandfather":"Hiashi Hyūga","adoptive aunt":"Hanabi Hyūga"},"jutsu":["Chakra Suppression Technique (Manga only)","Daikokuten (Manga only)","Disruption Cube (Manga only)","Kāma","Kāma Rift","Rasengan: \"Unison\"","Shadow Clone Technique","Sukunahikona (Manga only)"],"natureType":["Fire Release"],"personal":{"sex":"Male","species":"Celestial Being-Human hybrid","height":{"Boruto Manga":"183cm"},"kekkeiGenkai":"Isshiki's Dōjutsu   (Manga only)","affiliation":["Kara","Konohagakure"],"team":"Team 7","titles":["カワキKawaki","vessel(器,Utsuwa)"]},"rank":{"ninjaRank":{"Boruto Manga":"Genin"}},"tools":["Absorbing Hand","Bō","Microscopic Scientific Ninja Tools","Shinobi Gauntlet (Anime only)","Smoke-Flash Bomb (Anime only)"],"voiceActors":{"japanese":["Yūma Uchida","Shinya Hamazoe   (Boruto episode 1)"],"english":["Michael Schwalbe","Chris Niosi   (Boruto episode 1)"]}},{"id":755,"name":"Makibi","images":["https://static.wikia.nocookie.net/naruto/images/4/4c/Makibi.png"],"debut":{"anime":"Naruto Shippūden Episode #485","appearsIn":"Anime"},"personal":{"sex":"Male","occupation":"Businessman","affiliation":"Makibi Company\"Makibi Company\" is not in the list (Allied Shinobi Forces, Akatsuki, Root, Kara, Pale Blue Valley, Daidai Village, Aburame Clan, Academy, Advanced Technology Research Institute, Akagahara, ...) of allowed values for the \"Affiliation\" property."},"voiceActors":{"japanese":"Minoru Kawai","english":"Skip Stellrecht"}},{"id":762,"name":"Manda II","images":["https://static.wikia.nocookie.net/naruto/images/0/02/Manda_2.png","https://static.wikia.nocookie.net/naruto/images/3/3b/Manda_II.png"],"debut":{"manga":"Naruto Chapter #513","anime":"Naruto Shippūden Episode #255","game":"Naruto Mobile","appearsIn":"Anime, Manga, Game"},"family":{"genetic source":"Manda"},"jutsu":[],"personal":{"sex":"Male","species":"Snake","age":{"Part II":"1"},"classification":"Summon","affiliation":"Kabuto Yakushi\"Kabuto Yakushi\" is not in the list (Allied Shinobi Forces, Akatsuki, Root, Kara, Pale Blue Valley, Daidai Village, Aburame Clan, Academy, Advanced Technology Research Institute, Akagahara, ...) of allowed values for the \"Affiliation\" property.","titles":["二代目マンダNidaimeManda"]}},{"id":830,"name":"Renge Momoashi","images":[],"natureType":["Water Release"],"personal":{"sex":"Male","classification":"Missing-nin","affiliation":"Shuku Village\"Shuku Village\" is not in the list (Allied Shinobi Forces, Akatsuki, Root, Kara, Pale Blue Valley, Daidai Village, Aburame Clan, Academy, Advanced Technology Research Institute, Akagahara, ...) of allowed values for the \"Affiliation\" property.","team":"Team Shū"},"rank":{"ninjaRank":{"Part II":"Jōnin"}}},{"id":856,"name":"Naruto Musasabi","images":[],"natureType":["Wind Release","Lightning Release","Yang Release"],"personal":{"sex":"Male","classification":"Sage","affiliation":"Shuku Village\"Shuku Village\" is not in the list (Allied Shinobi Forces, Akatsuki, Root, Kara, Pale Blue Valley, Daidai Village, Aburame Clan, Academy, Advanced Technology Research Institute, Akagahara, ...) of allowed values for the \"Affiliation\" property.","team":"Team Shū","age":{"Academy Graduate":"6"}},"rank":{"ninjaRank":{"Part II":"Jōnin"}}},{"id":887,"name":"Nazuna","images":["https://static.wikia.nocookie.net/naruto/images/2/2b/Nazuna.png"],"debut":{"game":"Naruto: Path of the Ninja 2","appearsIn":"Game"},"family":{},"personal":{"sex":"Female","affiliation":"Valley of Great Evil\"Valley of Great Evil\" is not in the list (Allied Shinobi Forces, Akatsuki, Root, Kara, Pale Blue Valley, Daidai Village, Aburame Clan, Academy, Advanced Technology Research Institute, Akagahara, ...) of allowed values for the \"Affiliation\" property."}},{"id":912,"name":"Ōga","images":["https://static.wikia.nocookie.net/naruto/images/0/04/%C5%8Cga.png"],"debut":{"anime":"Boruto Episode #275","appearsIn":"Anime"},"jutsu":["Genjutsu Communication","Lightning Release: Lightning Eel","Lightning Release: Thunder Wedge","Puppet Technique"],"natureType":["Lightning Release","Yin Release"],"personal":{"sex":"Female","occupation":"Inner  (Former)","affiliation":"Kara"},"voiceActors":{"japanese":["Sara Matsumoto","Kappei Yamaguchi  (Male puppet)"]}},{"id":939,"name":"Isshiki Ōtsutsuki","images":["https://static.wikia.nocookie.net/naruto/images/2/21/Isshiki.png"],"debut":{"manga":"Boruto Chapter #35","anime":"Boruto Episode #202","game":"Naruto x Boruto: Ninja Voltage","appearsIn":"Anime, Manga, Game"},"family":{"adoptive son":"Kawaki","vessel":"Jigen"},"jutsu":["Daikokuten","Disruption Cube","Genjutsu Communication","Kāma Rift","Sukunahikona"],"natureType":["Yin Release","Fire Release  (Anime only)"],"personal":{"sex":"Male","species":"Celestial Being","status":"Deceased","kekkeiGenkai":["Byakugan","Isshiki's Dōjutsu"],"occupation":["Leader of Kara","Inner"],"affiliation":"Kara","partner":"Kaguya Ōtsutsuki","clan":"Ōtsutsuki"},"tools":["Bō"],"uniqueTraits":["Can absorb chakra"],"voiceActors":{"japanese":"Kenjirō Tsuda"}},{"id":960,"name":"Raimei","images":["https://static.wikia.nocookie.net/naruto/images/f/f8/Raimei.png"],"debut":{"anime":"Naruto Shippūden Episode #485","appearsIn":"Anime"},"natureType":["Lightning Release"],"personal":{"sex":"Male","affiliation":"Makibi Corporation\"Makibi Corporation\" is not in the list (Allied Shinobi Forces, Akatsuki, Root, Kara, Pale Blue Valley, Daidai Village, Aburame Clan, Academy, Advanced Technology Research Institute, Akagahara, ...) of allowed values for the \"Affiliation\" property."},"voiceActors":{"japanese":"Hirokazu Sekido","english":"Brian Donovan"}},{"id":1000,"name":"Sabu","images":["https://static.wikia.nocookie.net/naruto/images/8/8a/Sabu.png"],"debut":{"manga":"Naruto Chapter #468","anime":"Naruto Shippūden Episode #206","game":"Naruto Shippūden: Ultimate Ninja Impact","appearsIn":"Anime, Manga, Game"},"jutsu":["Yosaku Cut"],"personal":{"birthdate":"October 4","sex":"Male","age":{"Part II":"61"},"height":{"Part II":"130.5cm"},"weight":{"Part II":"37kg"},"bloodType":"O","occupation":"Enka Singer","affiliation":"Enka Ninja\"Enka Ninja\" is not in the list (Allied Shinobi Forces, Akatsuki, Root, Kara, Pale Blue Valley, Daidai Village, Aburame Clan, Academy, Advanced Technology Research Institute, Akagahara, ...) of allowed values for the \"Affiliation\" property.","partner":"Ponta"},"tools":["Axe"],"voiceActors":{"japanese":"Katsuhisa Hōki","english":"Michael Sorich"}},{"id":1027,"name":"Amado Sanzu","images":["https://static.wikia.nocookie.net/naruto/images/7/74/Amado.png"],"debut":{"manga":"Boruto Chapter #26","anime":"Boruto Episode #179","game":"Naruto x Boruto: Ninja Voltage","appearsIn":"Anime, Manga, Game"},"family":{"daughter":"Akebi Sanzu","creation/clone daughter":"Delta","creation":"Koji Kashin"},"jutsu":["Genjutsu Communication"],"natureType":["Yin Release"],"personal":{"sex":"Male","occupation":["Scientist","Inner  (Former)"],"affiliation":["Kara","Konohagakure"],"team":"Scientific Ninja Weapons Team"},"tools":["Space-Time Gate"],"voiceActors":{"japanese":"Akio Ōtsuka","english":"Greg Chun"}},{"id":1167,"name":"Suzuran","images":["https://static.wikia.nocookie.net/naruto/images/c/cc/Suzuran.png"],"debut":{"anime":"Naruto Shippūden Episode #485","appearsIn":"Anime"},"personal":{"sex":"Male","affiliation":"Himeyuri Company\"Himeyuri Company\" is not in the list (Allied Shinobi Forces, Akatsuki, Root, Kara, Pale Blue Valley, Daidai Village, Aburame Clan, Academy, Advanced Technology Research Institute, Akagahara, ...) of allowed values for the \"Affiliation\" property."}},{"id":1247,"name":"Garashi Tōno","images":["https://static.wikia.nocookie.net/naruto/images/4/4a/Garashi_T%C5%8Dno_Infobox.png"],"debut":{"anime":"Boruto Episode #157","appearsIn":"Anime"},"jutsu":["Shadow Clone Technique"],"personal":{"sex":"Male","status":"Deceased","occupation":"Outer","affiliation":["Amegakure","Kara"]},"voiceActors":{"japanese":"Kishō Taniyama","english":"Cory Yee"}},{"id":1284,"name":"Tsuyu","images":[],"natureType":["Wind Release"],"personal":{"sex":"Female","classification":"Medical-nin","affiliation":"Shuku Village\"Shuku Village\" is not in the list (Allied Shinobi Forces, Akatsuki, Root, Kara, Pale Blue Valley, Daidai Village, Aburame Clan, Academy, Advanced Technology Research Institute, Akagahara, ...) of allowed values for the \"Affiliation\" property.","team":"Team Shū"},"rank":{"ninjaRank":{"Part II":"Jōnin"}}},{"id":1346,"name":"Victor","images":["https://static.wikia.nocookie.net/naruto/images/9/90/Victor.png"],"debut":{"manga":"Boruto Chapter #15","anime":"Boruto Episode #157","game":"Naruto x Boruto: Ninja Voltage","appearsIn":"Anime, Manga, Game"},"jutsu":["Arm Growth Technique (Anime only)","Earth Release: Dust Storm (Anime only)","Earth Release: Tearing Earth Turning Palm (Anime only)","Fire Release: Great Fireball Technique (Anime only)","Fire Release: Great Flame Flower (Anime only)","Genjutsu Communication","Lightning Release: Heavenly Formation Lightning (Anime only)","Self-Healing Technique","Water Release: Water Formation Wall (Anime only)","Wind Release: Great Balloon (Anime only)"],"natureType":["Wind Release  (Anime only)","Lightning Release  (Anime only)","Earth Release  (Anime only)","Water Release  (Anime only)","Fire Release  (Anime only)","Yin Release"],"personal":{"sex":"Male","status":"Deceased","occupation":["Inner","Company President  (Anime only)"],"affiliation":["Kara","Allied Shinobi Forces  (Anime only)","Land of Valleys  (Anime only)"],"partner":"Deepa  (Anime only)"},"tools":["Shinobi Gauntlet","Space-Time Gate"],"voiceActors":{"japanese":"Chō","english":"Doug Stone"}},{"id":1347,"name":"Victor's Secretary","images":["https://static.wikia.nocookie.net/naruto/images/7/7a/Victor%27s_Secretary_Newshot.png"],"personal":{"sex":"Female","status":"Deceased","occupation":["Secretary","Outer"],"affiliation":["Land of Valleys","Kara"]},"voiceActors":{"japanese":"Hitomi Nabatame","english":"Anairis Quiñones"}}]